mensajes/__init__.py
mensajes/adios/__init__.py
mensajes/adios/despedidas.py
mensajes/hola/__init__.py
mensajes/hola/saludos.py
mensajes_aaron_galicia2610-6.0.dist-info/licenses/LICENSE
tests/__init__.py
tests/test_hola.py
mensajes_aaron_galicia2610-6.0.dist-info/METADATA
mensajes_aaron_galicia2610-6.0.dist-info/WHEEL
mensajes_aaron_galicia2610-6.0.dist-info/top_level.txt
mensajes_aaron_galicia2610-6.0.dist-info/RECORD
